{
    "15": {
        "31": [
            "اِلَّاۤ",
            "اِبۡلِيۡسَؕ",
            "اَبٰٓى",
            "اَنۡ",
            "يَّكُوۡنَ",
            "مَعَ",
            "السّٰجِدِيۡنَ‏",
            "٣١"
        ],
        "32": [
            "قَالَ",
            "يٰۤاِبۡلِيۡسُ",
            "مَا",
            "لَـكَ",
            "اَلَّا",
            "تَكُوۡنَ",
            "مَعَ",
            "السّٰجِدِيۡنَ‏",
            "٣٢"
        ],
        "33": [
            "قَالَ",
            "لَمۡ",
            "اَكُنۡ",
            "لِّاَسۡجُدَ",
            "لِبَشَرٍ",
            "خَلَقۡتَهٗ",
            "مِنۡ",
            "صَلۡصَالٍ",
            "مِّنۡ",
            "حَمَاٍ",
            "مَّسۡنُوۡنٍ‏",
            "٣٣"
        ],
        "34": [
            "قَالَ",
            "فَاخۡرُجۡ",
            "مِنۡهَا",
            "فَاِنَّكَ",
            "رَجِيۡمٌۙ‏",
            "٣٤"
        ],
        "35": [
            "وَّاِنَّ",
            "عَلَيۡكَ",
            "اللَّعۡنَةَ",
            "اِلٰى",
            "يَوۡمِ",
            "الدِّيۡنِ‏",
            "٣٥"
        ],
        "36": [
            "قَالَ",
            "رَبِّ",
            "فَاَنۡظِرۡنِىۡۤ",
            "اِلٰى",
            "يَوۡمِ",
            "يُبۡعَثُوۡنَ‏",
            "٣٦"
        ],
        "37": [
            "قَالَ",
            "فَاِنَّكَ",
            "مِنَ",
            "الۡمُنۡظَرِيۡنَۙ‏",
            "٣٧"
        ],
        "38": [
            "اِلٰى",
            "يَوۡمِ",
            "الۡوَقۡتِ",
            "الۡمَعۡلُوۡمِ‏",
            "٣٨"
        ],
        "39": [
            "قَالَ",
            "رَبِّ",
            "بِمَاۤ",
            "اَغۡوَيۡتَنِىۡ",
            "لَاُزَيِّنَنَّ",
            "لَهُمۡ",
            "فِى",
            "الۡاَرۡضِ",
            "وَلَاُغۡوِيَـنَّهُمۡ",
            "اَجۡمَعِيۡنَۙ‏",
            "٣٩"
        ],
        "40": [
            "اِلَّا",
            "عِبَادَكَ",
            "مِنۡهُمُ",
            "الۡمُخۡلَصِيۡنَ‏",
            "٤٠"
        ]
    }
}