{
    "2": {
        "241": [
            [
                "وَلِلۡمُطَلَّقَ<rule class=madda_normal>ـٰ</rule>تِ",
                "مَتَ<rule class=madda_normal>ـٰ</rule><rule class=iqlab>عُۢ</rule>",
                "<rule class=iqlab>ب</rule>ِ<rule class=ham_wasl>ٱ</rule>لۡمَعۡرُوفِ‌ۖ",
                "حَقًّا",
                "عَلَى",
                "<rule class=ham_wasl>ٱ</rule>لۡمُتَّق<rule class=madda_permissible>ِي</rule>نَ",
                "٢٤١"
            ]
        ],
        "242": [
            [
                "كَذ<rule class='madda_normal'>ٰ</rule>لِكَ",
                "يُبَيِّنُ",
                "<rule class=ham_wasl>ٱ</rule>للَّهُ",
                "لَكُمۡ",
                "ءَايَ<rule class=madda_normal>ـٰ</rule>تِه<rule class=madda_normal>ِۦ</rule>",
                "لَعَلَّكُمۡ",
                "تَعۡقِل<rule class=madda_permissible>ُو</rule>نَ",
                "٢٤٢"
            ]
        ],
        "243": [
            [
                "۞أَلَمۡ",
                "تَرَ",
                "إِلَى",
                "<rule class=ham_wasl>ٱ</rule>لَّذِينَ",
                "خَرَجُو<rule class=slnt>اۡ</rule>",
                "مِ<rule class=ikhafa>ن</rule>",
                "<rule class=ikhafa>د</rule>ِيَ<rule class=madda_normal>ـٰ</rule>رِهِمۡ",
                "وَهُمۡ",
                "أُلُوفٌ",
                "حَذَرَ",
                "<rule class=ham_wasl>ٱ</rule>لۡمَوۡتِ",
                "فَقَالَ",
                "لَهُمُ",
                "<rule class=ham_wasl>ٱ</rule>للَّهُ",
                "مُوتُو<rule class=slnt>اۡ</rule>",
                "ثُ<rule class=ghunnah>مّ</rule>َ",
                "أَحۡيَ<rule class=madda_normal>ـٰ</rule>هُمۡ‌ۚ",
                "إِ<rule class=ghunnah>نّ</rule>َ",
                "<rule class=ham_wasl>ٱ</rule>للَّهَ",
                "لَذُو",
                "فَضۡلٍ",
                "عَلَى",
                "<rule class=ham_wasl>ٱ</rule><rule class=laam_shamsiyah>ل</rule><rule class=ghunnah>نّ</rule>َاسِ",
                "وَلَ<rule class=madda_normal>ـٰ</rule>كِ<rule class=ghunnah>نّ</rule>َ",
                "أَكۡثَرَ",
                "<rule class=ham_wasl>ٱ</rule><rule class=laam_shamsiyah>ل</rule><rule class=ghunnah>نّ</rule>َاسِ",
                "لَا",
                "يَشۡكُر<rule class=madda_permissible>ُو</rule>نَ",
                "٢٤٣"
            ]
        ],
        "244": [
            [
                "وَقَ<rule class=madda_normal>ـٰ</rule>تِلُو<rule class=slnt>اۡ</rule>",
                "فِى",
                "سَبِيلِ",
                "<rule class=ham_wasl>ٱ</rule>للَّهِ",
                "وَ<rule class=ham_wasl>ٱ</rule>عۡلَم<rule class=madda_obligatory_mottasel>ُوٓ</rule><rule class=slnt>اۡ</rule>",
                "أَ<rule class=ghunnah>نّ</rule>َ",
                "<rule class=ham_wasl>ٱ</rule>للَّهَ",
                "سَمِيعٌ",
                "عَل<rule class=madda_permissible>ِي</rule>مٌ",
                "٢٤٤"
            ]
        ],
        "245": [
            [
                "مَّ<rule class=ikhafa>ن</rule>",
                "<rule class=ikhafa>ذ</rule>َا",
                "<rule class=ham_wasl>ٱ</rule>لَّذِى",
                "يُ<rule class=qalaqah>قۡ</rule>رِضُ",
                "<rule class=ham_wasl>ٱ</rule>للَّهَ",
                "قَرۡضًا",
                "حَسَ<rule class=ikhafa>نًا</rule>",
                "<rule class=ikhafa>ف</rule>َيُضَ<rule class=madda_normal>ـٰ</rule>عِفَهُ<rule class=madda_normal>ۥ</rule>",
                "لَهُ<rule class=madda_obligatory_monfasel>ۥٓ</rule>",
                "أَضۡعَا<rule class=ikhafa>فًا</rule>",
                "<rule class=ikhafa>ك</rule>َثِيرَ<rule class=idgham_ghunnah>ةً‌ۚ</rule>",
                "<rule class=idgham_ghunnah>و</rule>َ<rule class=ham_wasl>ٱ</rule>للَّهُ",
                "يَ<rule class=qalaqah>قۡ</rule>بِضُ",
                "وَيَ<rule class=qalaqah>بۡ</rule>صُۜطُ",
                "وَإِلَيۡهِ",
                "تُرۡجَع<rule class=madda_permissible>ُو</rule>نَ",
                "٢٤٥"
            ]
        ],
        "246": [
            [
                "أَلَمۡ",
                "تَرَ",
                "إِلَى",
                "<rule class=ham_wasl>ٱ</rule>لۡمَلَإِ",
                "م<rule class=iqlab>ِنۢ</rule>",
                "<rule class=iqlab>ب</rule>َن<rule class=madda_obligatory_monfasel>ِىٓ</rule>",
                "إِسۡر<rule class='madda_obligatory_mottasel'>ٰ</rule>ٓءِيلَ",
                "م<rule class=iqlab>ِنۢ</rule>",
                "<rule class=iqlab>ب</rule>َعۡدِ",
                "مُوسَ<rule class=madda_obligatory_monfasel>ىٰٓ</rule>",
                "إِذۡ",
                "قَالُو<rule class=slnt>اۡ</rule>",
                "لِنَبِ<rule class=idgham_wo_ghunnah>ىٍّ</rule>",
                "<rule class=idgham_wo_ghunnah>ل</rule>َّهُمُ",
                "<rule class=ham_wasl>ٱ</rule><rule class=qalaqah>بۡ</rule>عَثۡ",
                "لَنَا",
                "مَلِ<rule class=idgham_ghunnah>كًا</rule>",
                "<rule class=idgham_ghunnah>ن</rule>ُّقَ<rule class=madda_normal>ـٰ</rule>تِلۡ",
                "فِى",
                "سَبِيلِ",
                "<rule class=ham_wasl>ٱ</rule>للَّهِ‌ۖ",
                "قَالَ",
                "هَلۡ",
                "عَسَيۡتُمۡ",
                "إِ<rule class=ikhafa>ن</rule>",
                "<rule class=ikhafa>ك</rule>ُتِبَ",
                "عَلَيۡكُمُ",
                "<rule class=ham_wasl>ٱ</rule>لۡقِتَالُ",
                "أَلَّا",
                "تُقَ<rule class=madda_normal>ـٰ</rule>تِلُو<rule class=slnt>اۡ‌ۖ</rule>",
                "قَالُو<rule class=slnt>اۡ</rule>",
                "وَمَا",
                "لَن<rule class=madda_obligatory_monfasel>َآ</rule>",
                "أَلَّا",
                "نُقَ<rule class=madda_normal>ـٰ</rule>تِلَ",
                "فِى",
                "سَبِيلِ",
                "<rule class=ham_wasl>ٱ</rule>للَّهِ",
                "وَقَ<rule class=qalaqah>دۡ</rule>",
                "أُخۡرِ<rule class=qalaqah>جۡ</rule>نَا",
                "مِ<rule class=ikhafa>ن</rule>",
                "<rule class=ikhafa>د</rule>ِيَ<rule class=madda_normal>ـٰ</rule>رِنَا",
                "وَأَ<rule class=qalaqah>بۡ</rule>ن<rule class=madda_obligatory_mottasel>َا</rule>ٓئِنَا‌ۖ",
                "فَلَ<rule class=ghunnah>مّ</rule>َا",
                "كُتِبَ",
                "عَلَيۡهِمُ",
                "<rule class=ham_wasl>ٱ</rule>لۡقِتَالُ",
                "تَوَلَّوۡ<rule class=slnt>اۡ</rule>",
                "إِلَّا",
                "قَلِيل<rule class=idgham_ghunnah>اً</rule>",
                "<rule class=idgham_ghunnah>م</rule>ِّنۡهُمۡ‌ۗ",
                "وَ<rule class=ham_wasl>ٱ</rule>للَّهُ",
                "عَلِي<rule class=iqlab>مُۢ</rule>",
                "<rule class=iqlab>ب</rule>ِ<rule class=ham_wasl>ٱ</rule><rule class=laam_shamsiyah>ل</rule>ظَّ<rule class=madda_normal>ـٰ</rule>لِم<rule class=madda_permissible>ِي</rule>نَ",
                "٢٤٦"
            ]
        ],
        "247": [
            [
                "وَقَالَ",
                "لَهُمۡ",
                "نَبِيُّهُمۡ",
                "إِ<rule class=ghunnah>نّ</rule>َ",
                "<rule class=ham_wasl>ٱ</rule>للَّهَ",
                "قَ<rule class=qalaqah>دۡ</rule>",
                "بَعَثَ",
                "لَكُمۡ",
                "طَالُوتَ",
                "مَلِ<rule class=ikhafa>كًا‌ۚ</rule>",
                "<rule class=ikhafa>ق</rule>َال<rule class=madda_obligatory_mottasel>ُوٓ</rule><rule class=slnt>اۡ</rule>",
                "أَ<rule class=ghunnah>نّ</rule>َىٰ",
                "يَكُونُ",
                "لَهُ",
                "<rule class=ham_wasl>ٱ</rule>لۡمُلۡكُ",
                "عَلَيۡنَا",
                "وَنَحۡنُ",
                "أَحَقُّ",
                "بِ<rule class=ham_wasl>ٱ</rule>لۡمُلۡكِ",
                "مِنۡهُ",
                "وَلَمۡ",
                "يُؤۡتَ",
                "سَعَ<rule class=idgham_ghunnah>ةً</rule>",
                "<rule class=idgham_ghunnah>م</rule>ِّنَ",
                "<rule class=ham_wasl>ٱ</rule>لۡمَالِ‌ۚ",
                "قَالَ",
                "إِ<rule class=ghunnah>نّ</rule>َ",
                "<rule class=ham_wasl>ٱ</rule>للَّهَ",
                "<rule class=ham_wasl>ٱ</rule>صۡطَفَ<rule class=madda_normal>ـٰ</rule>هُ",
                "عَلَيۡكُمۡ",
                "وَزَادَهُ<rule class=madda_normal>ۥ</rule>",
                "بَسۡطَ<rule class=ikhafa>ةً</rule>",
                "<rule class=ikhafa>ف</rule>ِى",
                "<rule class=ham_wasl>ٱ</rule>لۡعِلۡمِ",
                "وَ<rule class=ham_wasl>ٱ</rule>لۡجِسۡمِ‌ۖ",
                "وَ<rule class=ham_wasl>ٱ</rule>للَّهُ",
                "يُؤۡتِى",
                "مُلۡكَهُ<rule class=madda_normal>ۥ</rule>",
                "م<rule class=idgham_ghunnah>َن</rule>",
                "<rule class=idgham_ghunnah>ي</rule>َش<rule class=madda_obligatory_mottasel>َا</rule>ٓءُ‌ۚ",
                "وَ<rule class=ham_wasl>ٱ</rule>للَّهُ",
                "و<rule class='madda_normal'>ٰ</rule>سِعٌ",
                "عَل<rule class=madda_permissible>ِي</rule>مٌ",
                "٢٤٧"
            ]
        ],
        "248": [
            [
                "وَقَالَ",
                "لَهُمۡ",
                "نَبِيُّهُمۡ",
                "إِ<rule class=ghunnah>نّ</rule>َ",
                "ءَايَةَ",
                "مُلۡكِه<rule class=madda_obligatory_monfasel>ِۦٓ</rule>",
                "أ<rule class=idgham_ghunnah>َن</rule>",
                "<rule class=idgham_ghunnah>ي</rule>َأۡتِيَكُمُ",
                "<rule class=ham_wasl>ٱ</rule><rule class=laam_shamsiyah>ل</rule>تَّابُوتُ",
                "فِيهِ",
                "سَكِينَ<rule class=idgham_ghunnah>ةٌ</rule>",
                "<rule class=idgham_ghunnah>م</rule>ّ<rule class=idgham_wo_ghunnah>ِن</rule>",
                "<rule class=idgham_wo_ghunnah>ر</rule>َّبِّكُمۡ",
                "وَبَقِيَّ<rule class=idgham_ghunnah>ةٌ</rule>",
                "<rule class=idgham_ghunnah>م</rule>ِّ<rule class=ghunnah>مّ</rule>َا",
                "تَرَكَ",
                "ءَالُ",
                "مُوسَىٰ",
                "وَءَالُ",
                "هَ<rule class=madda_normal>ـٰ</rule>رُونَ",
                "تَحۡمِلُهُ",
                "<rule class=ham_wasl>ٱ</rule>لۡمَلَ<rule class=madda_obligatory_mottasel>ـٰٓ</rule>ئِكَةُ‌ۚ",
                "إِ<rule class=ghunnah>نّ</rule>َ",
                "فِى",
                "ذ<rule class='madda_normal'>ٰ</rule>لِكَ",
                "لَأَيَ<rule class=idgham_wo_ghunnah>ةً</rule>",
                "<rule class=idgham_wo_ghunnah>ل</rule>َّكُمۡ",
                "إِ<rule class=ikhafa>ن</rule>",
                "<rule class=ikhafa>ك</rule>ُ<rule class=ikhafa>نت</rule><rule class=idgham_shafawi>ُم</rule>",
                "<rule class=idgham_shafawi>م</rule>ُّؤۡمِن<rule class=madda_permissible>ِي</rule>نَ",
                "٢٤٨"
            ]
        ],
        "249": [
            [
                "فَلَ<rule class=ghunnah>مّ</rule>َا",
                "فَصَلَ",
                "طَالُوتُ",
                "بِ<rule class=ham_wasl>ٱ</rule>لۡجُنُودِ",
                "قَالَ",
                "إِ<rule class=ghunnah>نّ</rule>َ",
                "<rule class=ham_wasl>ٱ</rule>للَّهَ",
                "مُ<rule class=qalaqah>بۡ</rule>تَلِيك<rule class=ikhafa_shafawi>ُم</rule>",
                "<rule class=ikhafa_shafawi>ب</rule>ِنَهَ<rule class=ikhafa>رٍ</rule>",
                "<rule class=ikhafa>ف</rule>َمَ<rule class=ikhafa>ن</rule>",
                "<rule class=ikhafa>ش</rule>َرِبَ",
                "مِنۡهُ",
                "فَلَيۡسَ",
                "مِ<rule class=ghunnah>نّ</rule>ِى",
                "وَم<rule class=idgham_wo_ghunnah>َن</rule>",
                "<rule class=idgham_wo_ghunnah>ل</rule>َّمۡ",
                "يَ<rule class=qalaqah>طۡ</rule>عَمۡهُ",
                "فَإِ<rule class=ghunnah>نّ</rule>َهُ<rule class=madda_normal>ۥ</rule>",
                "مِ<rule class=ghunnah>نّ</rule><rule class=madda_obligatory_monfasel>ِىٓ</rule>",
                "إِلَّا",
                "مَنِ",
                "<rule class=ham_wasl>ٱ</rule>غۡتَرَفَ",
                "غُرۡفَ<rule class=iqlab>ةَۢ</rule>",
                "<rule class=iqlab>ب</rule>ِيَدِه<rule class=madda_normal>ِۦ</rule>‌ۚ",
                "فَشَرِبُو<rule class=slnt>اۡ</rule>",
                "مِنۡهُ",
                "إِلَّا",
                "قَلِيل<rule class=idgham_ghunnah>اً</rule>",
                "<rule class=idgham_ghunnah>م</rule>ِّنۡهُمۡ‌ۚ",
                "فَلَ<rule class=ghunnah>مّ</rule>َا",
                "جَاوَزَهُ<rule class=madda_normal>ۥ</rule>",
                "هُوَ",
                "وَ<rule class=ham_wasl>ٱ</rule>لَّذِينَ",
                "ءَامَنُو<rule class=slnt>اۡ</rule>",
                "مَعَهُ<rule class=madda_normal>ۥ</rule>",
                "قَالُو<rule class=slnt>اۡ</rule>",
                "لَا",
                "طَاقَةَ",
                "لَنَا",
                "<rule class=ham_wasl>ٱ</rule>لۡيَوۡمَ",
                "بِجَالُوتَ",
                "وَجُنُودِه<rule class=madda_normal>ِۦ</rule>‌ۚ",
                "قَالَ",
                "<rule class=ham_wasl>ٱ</rule>لَّذِينَ",
                "يَظُ<rule class=ghunnah>نّ</rule>ُونَ",
                "أَ<rule class=ghunnah>نّ</rule>َه<rule class=idgham_shafawi>ُم</rule>",
                "<rule class=idgham_shafawi>م</rule>ُّلَ<rule class=madda_normal>ـٰ</rule>قُو<rule class=slnt>اۡ</rule>",
                "<rule class=ham_wasl>ٱ</rule>للَّهِ",
                "ك<rule class=idgham_shafawi>َم</rule>",
                "<rule class=idgham_shafawi>م</rule>ِّ<rule class=ikhafa>ن</rule>",
                "<rule class=ikhafa>ف</rule>ِئَ<rule class=ikhafa>ةٍ</rule>",
                "<rule class=ikhafa>ق</rule>َلِيلَةٍ",
                "غَلَبَتۡ",
                "فِئَ<rule class=ikhafa>ةً</rule>",
                "<rule class=ikhafa>ك</rule>َثِيرَ<rule class=iqlab>ةَۢ</rule>",
                "<rule class=iqlab>ب</rule>ِإِذۡنِ",
                "<rule class=ham_wasl>ٱ</rule>للَّهِ‌ۗ",
                "وَ<rule class=ham_wasl>ٱ</rule>للَّهُ",
                "مَعَ",
                "<rule class=ham_wasl>ٱ</rule><rule class=laam_shamsiyah>ل</rule>صَّ<rule class=madda_normal>ـٰ</rule>بِر<rule class=madda_permissible>ِي</rule>نَ",
                "٢٤٩"
            ]
        ],
        "250": [
            [
                "وَلَ<rule class=ghunnah>مّ</rule>َا",
                "بَرَزُو<rule class=slnt>اۡ</rule>",
                "لِجَالُوتَ",
                "وَجُنُودِه<rule class=madda_normal>ِۦ</rule>",
                "قَالُو<rule class=slnt>اۡ</rule>",
                "رَبَّن<rule class=madda_obligatory_monfasel>َآ</rule>",
                "أَفۡرِغۡ",
                "عَلَيۡنَا",
                "صَ<rule class=qalaqah>بۡ</rule><rule class=idgham_ghunnah>رًا</rule>",
                "<rule class=idgham_ghunnah>و</rule>َثَبِّتۡ",
                "أَ<rule class=qalaqah>قۡ</rule>دَامَنَا",
                "وَ<rule class=ham_wasl>ٱ</rule><rule class=ikhafa>نص</rule>ُرۡنَا",
                "عَلَى",
                "<rule class=ham_wasl>ٱ</rule>لۡقَوۡمِ",
                "<rule class=ham_wasl>ٱ</rule>لۡكَ<rule class=madda_normal>ـٰ</rule>فِر<rule class=madda_permissible>ِي</rule>نَ",
                "٢٥٠"
            ]
        ]
    }
}